flappy_bird_gym/__init__.py
flappy_bird_gym/cli.py
flappy_bird_gym/original_game.py
flappy_bird_gym/assets/audio/die.ogg
flappy_bird_gym/assets/audio/die.wav
flappy_bird_gym/assets/audio/hit.ogg
flappy_bird_gym/assets/audio/hit.wav
flappy_bird_gym/assets/audio/point.ogg
flappy_bird_gym/assets/audio/point.wav
flappy_bird_gym/assets/audio/swoosh.ogg
flappy_bird_gym/assets/audio/swoosh.wav
flappy_bird_gym/assets/audio/wing.ogg
flappy_bird_gym/assets/audio/wing.wav
flappy_bird_gym/assets/sprites/0.png
flappy_bird_gym/assets/sprites/1.png
flappy_bird_gym/assets/sprites/2.png
flappy_bird_gym/assets/sprites/3.png
flappy_bird_gym/assets/sprites/4.png
flappy_bird_gym/assets/sprites/5.png
flappy_bird_gym/assets/sprites/6.png
flappy_bird_gym/assets/sprites/7.png
flappy_bird_gym/assets/sprites/8.png
flappy_bird_gym/assets/sprites/9.png
flappy_bird_gym/assets/sprites/background-day.png
flappy_bird_gym/assets/sprites/background-night.png
flappy_bird_gym/assets/sprites/base.png
flappy_bird_gym/assets/sprites/bluebird-downflap.png
flappy_bird_gym/assets/sprites/bluebird-midflap.png
flappy_bird_gym/assets/sprites/bluebird-upflap.png
flappy_bird_gym/assets/sprites/gameover.png
flappy_bird_gym/assets/sprites/message.png
flappy_bird_gym/assets/sprites/pipe-green.png
flappy_bird_gym/assets/sprites/pipe-red.png
flappy_bird_gym/assets/sprites/redbird-downflap.png
flappy_bird_gym/assets/sprites/redbird-midflap.png
flappy_bird_gym/assets/sprites/redbird-upflap.png
flappy_bird_gym/assets/sprites/yellowbird-downflap.png
flappy_bird_gym/assets/sprites/yellowbird-midflap.png
flappy_bird_gym/assets/sprites/yellowbird-upflap.png
flappy_bird_gym/envs/__init__.py
flappy_bird_gym/envs/flappy_bird_env_rgb.py
flappy_bird_gym/envs/flappy_bird_env_simple.py
flappy_bird_gym/envs/game_logic.py
flappy_bird_gym/envs/renderer.py
flappy_bird_gym/envs/utils.py
flappy_bird_gym-0.3.0.dist-info/LICENSE
flappy_bird_gym-0.3.0.dist-info/METADATA
flappy_bird_gym-0.3.0.dist-info/WHEEL
flappy_bird_gym-0.3.0.dist-info/entry_points.txt
flappy_bird_gym-0.3.0.dist-info/top_level.txt
flappy_bird_gym-0.3.0.dist-info/RECORD
