Metadata-Version: 2.1
Name: flappy-bird-gym
Version: 0.3.0
Summary: An OpenAI gym environment for the Flappy Bird game.
Home-page: https://github.com/Talendar/flappy-bird-gym
Author: Gabriel Guedes Nogueira (Talendar)
Author-email: gabriel.gnogueira@gmail.com
License: MIT License
Download-URL: https://github.com/Talendar/flappy-bird-gym/releases
Keywords: Flappy-BirdGame Gym OpenAI-Gym Reinforcement-Learning Reinforcement-Learning-Environment
Platform: UNKNOWN
Classifier: Programming Language :: Python :: 3
Classifier: Programming Language :: Python :: 3 :: Only
Classifier: Programming Language :: Python :: 3.6
Classifier: Programming Language :: Python :: 3.7
Classifier: Programming Language :: Python :: 3.8
Classifier: Programming Language :: Python :: 3.9
Classifier: License :: OSI Approved :: MIT License
Classifier: Operating System :: OS Independent
Classifier: Intended Audience :: Developers
Classifier: Intended Audience :: Education
Classifier: Intended Audience :: Science/Research
Classifier: Topic :: Scientific/Engineering
Classifier: Topic :: Scientific/Engineering :: Mathematics
Classifier: Topic :: Scientific/Engineering :: Artificial Intelligence
Classifier: Topic :: Software Development
Classifier: Topic :: Software Development :: Libraries
Classifier: Topic :: Software Development :: Libraries :: Python Modules
Requires-Python: >=3.6
